{
  "id": "73f3385c-1518-46c4-9e18-c87cac5aa64f",
  "prevId": "50304a68-8ef0-4aec-aa80-8dd234b36ebb",
  "version": "7",
  "dialect": "postgresql",
  "tables": {
    "public.eventCategory": {
      "name": "eventCategory",
      "schema": "",
      "columns": {
        "id": {
          "name": "id",
          "type": "serial",
          "primaryKey": true,
          "notNull": true
        },
        "userId": {
          "name": "userId",
          "type": "integer",
          "primaryKey": false,
          "notNull": false
        },
        "name": {
          "name": "name",
          "type": "varchar(100)",
          "primaryKey": false,
          "notNull": true
        },
        "emoji": {
          "name": "emoji",
          "type": "varchar(32)",
          "primaryKey": false,
          "notNull": false
        },
        "color": {
          "name": "color",
          "type": "integer",
          "primaryKey": false,
          "notNull": false
        },
        "createdAt": {
          "name": "createdAt",
          "type": "timestamp",
          "primaryKey": false,
          "notNull": true,
          "default": "now()"
        },
        "updatedAt": {
          "name": "updatedAt",
          "type": "timestamp",
          "primaryKey": false,
          "notNull": true,
          "default": "now()"
        }
      },
      "indexes": {},
      "foreignKeys": {
        "eventCategory_userId_user_id_fk": {
          "name": "eventCategory_userId_user_id_fk",
          "tableFrom": "eventCategory",
          "tableTo": "user",
          "columnsFrom": [
            "userId"
          ],
          "columnsTo": [
            "id"
          ],
          "onDelete": "no action",
          "onUpdate": "no action"
        }
      },
      "compositePrimaryKeys": {},
      "uniqueConstraints": {
        "event_name_user_id": {
          "name": "event_name_user_id",
          "nullsNotDistinct": false,
          "columns": [
            "name",
            "userId"
          ]
        }
      },
      "policies": {},
      "checkConstraints": {},
      "isRLSEnabled": false
    },
    "public.event": {
      "name": "event",
      "schema": "",
      "columns": {
        "id": {
          "name": "id",
          "type": "serial",
          "primaryKey": true,
          "notNull": true
        },
        "userId": {
          "name": "userId",
          "type": "integer",
          "primaryKey": false,
          "notNull": false
        },
        "name": {
          "name": "name",
          "type": "varchar(255)",
          "primaryKey": false,
          "notNull": false
        },
        "formattedMessage": {
          "name": "formattedMessage",
          "type": "text",
          "primaryKey": false,
          "notNull": false
        },
        "fields": {
          "name": "fields",
          "type": "jsonb",
          "primaryKey": false,
          "notNull": false
        },
        "eventCategoryId": {
          "name": "eventCategoryId",
          "type": "integer",
          "primaryKey": false,
          "notNull": false
        },
        "deliveryStatus": {
          "name": "deliveryStatus",
          "type": "deliveryStatusEnum",
          "typeSchema": "public",
          "primaryKey": false,
          "notNull": false,
          "default": "'PENDING'"
        },
        "createdAt": {
          "name": "createdAt",
          "type": "timestamp",
          "primaryKey": false,
          "notNull": true,
          "default": "now()"
        },
        "updatedAt": {
          "name": "updatedAt",
          "type": "timestamp",
          "primaryKey": false,
          "notNull": true,
          "default": "now()"
        }
      },
      "indexes": {
        "createdAt_idx": {
          "name": "createdAt_idx",
          "columns": [
            {
              "expression": "createdAt",
              "isExpression": false,
              "asc": true,
              "nulls": "last"
            }
          ],
          "isUnique": false,
          "concurrently": false,
          "method": "btree",
          "with": {}
        },
        "fields_idx": {
          "name": "fields_idx",
          "columns": [
            {
              "expression": "fields",
              "isExpression": false,
              "asc": true,
              "nulls": "last"
            }
          ],
          "isUnique": false,
          "concurrently": false,
          "method": "btree",
          "with": {}
        }
      },
      "foreignKeys": {
        "event_userId_user_id_fk": {
          "name": "event_userId_user_id_fk",
          "tableFrom": "event",
          "tableTo": "user",
          "columnsFrom": [
            "userId"
          ],
          "columnsTo": [
            "id"
          ],
          "onDelete": "no action",
          "onUpdate": "no action"
        },
        "event_eventCategoryId_eventCategory_id_fk": {
          "name": "event_eventCategoryId_eventCategory_id_fk",
          "tableFrom": "event",
          "tableTo": "eventCategory",
          "columnsFrom": [
            "eventCategoryId"
          ],
          "columnsTo": [
            "id"
          ],
          "onDelete": "cascade",
          "onUpdate": "no action"
        }
      },
      "compositePrimaryKeys": {},
      "uniqueConstraints": {},
      "policies": {},
      "checkConstraints": {},
      "isRLSEnabled": false
    },
    "public.quota": {
      "name": "quota",
      "schema": "",
      "columns": {
        "id": {
          "name": "id",
          "type": "serial",
          "primaryKey": true,
          "notNull": true
        },
        "userId": {
          "name": "userId",
          "type": "integer",
          "primaryKey": false,
          "notNull": false
        },
        "count": {
          "name": "count",
          "type": "integer",
          "primaryKey": false,
          "notNull": true,
          "default": 0
        },
        "month": {
          "name": "month",
          "type": "integer",
          "primaryKey": false,
          "notNull": false
        },
        "year": {
          "name": "year",
          "type": "integer",
          "primaryKey": false,
          "notNull": false
        },
        "createdAt": {
          "name": "createdAt",
          "type": "timestamp",
          "primaryKey": false,
          "notNull": true,
          "default": "now()"
        },
        "updatedAt": {
          "name": "updatedAt",
          "type": "timestamp",
          "primaryKey": false,
          "notNull": true,
          "default": "now()"
        }
      },
      "indexes": {},
      "foreignKeys": {
        "quota_userId_user_id_fk": {
          "name": "quota_userId_user_id_fk",
          "tableFrom": "quota",
          "tableTo": "user",
          "columnsFrom": [
            "userId"
          ],
          "columnsTo": [
            "id"
          ],
          "onDelete": "no action",
          "onUpdate": "no action"
        }
      },
      "compositePrimaryKeys": {},
      "uniqueConstraints": {},
      "policies": {},
      "checkConstraints": {},
      "isRLSEnabled": false
    },
    "public.user": {
      "name": "user",
      "schema": "",
      "columns": {
        "id": {
          "name": "id",
          "type": "serial",
          "primaryKey": true,
          "notNull": true
        },
        "externalId": {
          "name": "externalId",
          "type": "text",
          "primaryKey": false,
          "notNull": false
        },
        "email": {
          "name": "email",
          "type": "varchar(255)",
          "primaryKey": false,
          "notNull": true
        },
        "discordId": {
          "name": "discordId",
          "type": "varchar(255)",
          "primaryKey": false,
          "notNull": false
        },
        "apiKey": {
          "name": "apiKey",
          "type": "uuid",
          "primaryKey": false,
          "notNull": false,
          "default": "gen_random_uuid()"
        },
        "plan": {
          "name": "plan",
          "type": "plan",
          "typeSchema": "public",
          "primaryKey": false,
          "notNull": false,
          "default": "'FREE'"
        },
        "createdAt": {
          "name": "createdAt",
          "type": "timestamp",
          "primaryKey": false,
          "notNull": true,
          "default": "now()"
        },
        "updatedAt": {
          "name": "updatedAt",
          "type": "timestamp",
          "primaryKey": false,
          "notNull": true,
          "default": "now()"
        },
        "quotaLimit": {
          "name": "quotaLimit",
          "type": "integer",
          "primaryKey": false,
          "notNull": false
        }
      },
      "indexes": {
        "apiKey_idx": {
          "name": "apiKey_idx",
          "columns": [
            {
              "expression": "apiKey",
              "isExpression": false,
              "asc": true,
              "nulls": "last"
            }
          ],
          "isUnique": false,
          "concurrently": false,
          "method": "btree",
          "with": {}
        },
        "email_idx": {
          "name": "email_idx",
          "columns": [
            {
              "expression": "email",
              "isExpression": false,
              "asc": true,
              "nulls": "last"
            }
          ],
          "isUnique": false,
          "concurrently": false,
          "method": "btree",
          "with": {}
        }
      },
      "foreignKeys": {},
      "compositePrimaryKeys": {},
      "uniqueConstraints": {
        "user_email_unique": {
          "name": "user_email_unique",
          "nullsNotDistinct": false,
          "columns": [
            "email"
          ]
        }
      },
      "policies": {},
      "checkConstraints": {},
      "isRLSEnabled": false
    }
  },
  "enums": {
    "public.deliveryStatusEnum": {
      "name": "deliveryStatusEnum",
      "schema": "public",
      "values": [
        "PENDING",
        "FAILED",
        "DELIVERED"
      ]
    },
    "public.plan": {
      "name": "plan",
      "schema": "public",
      "values": [
        "FREE",
        "PRO"
      ]
    }
  },
  "schemas": {},
  "sequences": {},
  "roles": {},
  "policies": {},
  "views": {},
  "_meta": {
    "columns": {},
    "schemas": {},
    "tables": {}
  }
}